notion_upload/__init__.py
notion_upload/core.py
notion_upload/mime_types.json
notion_upload-1.3.2.dist-info/licenses/LICENSE
tests/test_core.py
notion_upload-1.3.2.dist-info/METADATA
notion_upload-1.3.2.dist-info/WHEEL
notion_upload-1.3.2.dist-info/top_level.txt
notion_upload-1.3.2.dist-info/RECORD
