Metadata-Version: 2.4
Name: notion_upload
Version: 1.3.2
Summary: A simple library that handles uploading files to Notion
Author-email: Michael Masarik <masarikfamilymichael@gmail.com>
License-Expression: MIT
Project-URL: Homepage, https://github.com/michael-masarik/notion_upload
Project-URL: Repository, https://github.com/michael-masarik/notion_upload
Project-URL: Issues, https://github.com/michael-masarik/notion_upload/issues
Keywords: notion,upload,api,python
Classifier: Programming Language :: Python :: 3
Classifier: Operating System :: OS Independent
Classifier: Topic :: Software Development :: Libraries
Requires-Python: >=3.8
License-File: LICENSE
Requires-Dist: requests
Provides-Extra: dev
Requires-Dist: pytest; extra == "dev"
Dynamic: license-file
